alu.v
module alu(
  input logic[31:0] reg_read_a,
  input logic[31:0] alub,
  input logic[3:0] ALUcon,
  input logic unsign,
  output logic eq,
  output logic lt,
  output logic[31:0] ALUoutput,
  output logic[31:0] lo,
  output logic[31:0] hi 
);

logic[63:0] multiplier;
typedef enum logic[3:0]{
    OPCODE_ADD = 4'd0,
    OPCODE_SUB = 4'd1,
    OPCODE_AND = 4'd2,
    OPCODE_OR = 4'd3,
    OPCODE_SLT = 4'd4,
    OPCODE_DIV = 4'd5,
    OPCODE_MULT = 4'd6,
    OPCODE_SLL = 4'd7,
    OPCODE_XOR = 4'd8,
    OPCODE_SRA = 4'd9,
    OPCODE_SRL = 4'd10
} opcode_t;

    always @(*)  begin
        eq=0;
        lt=0;
        hi=0;
        lo=0;
        if (ALUcon == OPCODE_ADD) begin
            if (unsign ==0) begin
                ALUoutput= reg_read_a + alub;
            end
            else begin
                ALUoutput= $unsigned(reg_read_a) + $unsigned(alub);
            end

        end
        else if (ALUcon == OPCODE_SUB) begin
            if (unsign==0) begin
                ALUoutput = $signed(reg_read_a) - $signed(alub);
                if (($signed(reg_read_a)-$signed(alub))==0) begin
                    eq=1;
                end
                else if (($signed(reg_read_a)-$signed(alub))<0) begin
                    lt=1;
                end
                else begin
                    lt=0;
                end
                
            end
            else if (unsign==1) begin
                ALUoutput = $unsigned(reg_read_a) - $unsigned(alub);
                if (($unsigned(reg_read_a)-$unsigned(alub))==0) begin
                    eq=1;
                end
                else if (($unsigned(reg_read_a)-$unsigned(alub))<0) begin
                    $display("%d", $unsigned(reg_read_a)-$unsigned(alub));
                    lt=1;
                end
                else begin
                    lt=0;
                end
            end
        end
        else if (ALUcon == OPCODE_AND) begin
            ALUoutput = reg_read_a & alub;
        end
        else if (ALUcon== OPCODE_OR) begin
            ALUoutput = reg_read_a | alub;
        end
        else if (ALUcon == OPCODE_SLT) begin
            if (unsign ==0) begin
                if (reg_read_a<alub) begin
                    ALUoutput = 32'd 1;
                end
                else begin
                    ALUoutput = 32'd 0;
                end     
            end
            else if (unsign==1) begin
                if ($unsigned(reg_read_a)<$unsigned(alub)) begin
                    ALUoutput = 32'd 1;
                end
                else begin
                    ALUoutput = 32'd 0;
                end 
            end
            
        end
        else if (ALUcon == OPCODE_DIV) begin
            if (unsign ==0) begin
                hi = $signed(reg_read_a) % $signed(alub);
                lo = $signed(reg_read_a)/$signed(alub);
            end
            else if (unsign ==1) begin
                hi = $unsigned(reg_read_a) % $unsigned(alub);
                lo = $unsigned(reg_read_a)/$unsigned(alub);
            end
            
        end
        else if (ALUcon == OPCODE_MULT) begin
            if (unsign ==0) begin
                multiplier = $signed(reg_read_a) *$signed(alub);
                hi = multiplier[63:32];
                lo = multiplier[31:0];
                 
            end
            else if (unsign ==1) begin
                multiplier = $unsigned(reg_read_a) *$unsigned(alub);
                hi = multiplier[63:32];
                lo = multiplier[31:0];
            end
            
        end
        else if (ALUcon == OPCODE_SLL) begin
            ALUoutput = reg_read_a << alub;
        end
        else if (ALUcon == OPCODE_XOR) begin
            ALUoutput = reg_read_a ^ alub;
        end
        else if (ALUcon == OPCODE_SRA) begin
            ALUoutput = reg_read_a>>>alub;
        end
        else if (ALUcon == OPCODE_SRL) begin
            ALUoutput = reg_read_a >>alub;
        end
    end
    
endmodule

alu_tb.v
module alu_tb();
    logic[31:0] reg_read_a;
    logic[31:0] alub;
    logic[3:0] ALUcon;
    logic unsign;
    logic eq;
    logic lt;
    logic[31:0] ALUoutput;
    logic[31:0] lo;
    logic[31:0] hi; 

    alu dut(
        .reg_read_a(reg_read_a),
        .alub(alub), 
        .ALUcon(ALUcon), 
        .unsign(unsign),
        .eq(eq), 
        .lt(lt), 
        .ALUoutput(ALUoutput), 
        .lo(lo),
        .hi(hi)
    );

//Without Loop
    initial begin
        $dumpfile("alu_tb.vcd");
        $dumpvars(0,alu_tb);
        #1;
        unsign=0;
        reg_read_a = 34;
        alub = 10;
        ALUcon = 0;
        #1;
        assert(ALUoutput==44);
        ALUcon = 1;
        #1;
        assert(ALUoutput==24);
        ALUcon = 2;
        #1;
        assert(ALUoutput ==2 );
        ALUcon = 3;
        #1;
        assert(ALUoutput== 42);
        ALUcon = 4;
        #1;
        assert (ALUoutput == 0);
        ALUcon = 5;
        #1;
        assert(hi==4);
        assert(lo== 3);
        ALUcon = 6;
        #1;
        assert(hi==0);
        assert(lo == 340);
        ALUcon = 7;
        #1;
        assert(ALUoutput == 34816);
        ALUcon = 8;
        #1;
        assert(ALUoutput == 40);
        ALUcon =9;
        #1;
        assert(ALUoutput == 0);
        ALUcon =10;
        #1
        assert(ALUoutput ==0);
        $display("Passed testcase a =34, b=10");
        #1;
        reg_read_a = 10;
        alub = 34;
        ALUcon = 0;
        #1;
        assert(ALUoutput==44);
        ALUcon = 1;
        #1;
        assert(ALUoutput==-24);
        ALUcon = 2;
        #1;
        assert(ALUoutput ==2 );
        ALUcon = 3;
        #1;
        assert(ALUoutput== 42);
        ALUcon = 4;
        #1;
        assert (ALUoutput == 1);
        ALUcon = 5;
        #1;
        assert(hi==10);
        assert(lo== 0);
        ALUcon = 6;
        #1;
        assert(hi==0);
        assert(lo == 340);
        ALUcon = 7;
        #1;
        assert(ALUoutput == 0);
        ALUcon = 8;
        #1;
        assert(ALUoutput == 40);
        ALUcon =9;
        #1;
        assert(ALUoutput == 0);
        ALUcon =10;
        #1
        assert(ALUoutput ==0);
        $display("Passed testcase a =10, b=34");
        reg_read_a = 32'b11111111111111111111101010110111;
        alub = 10;
        unsign =0;
        ALUcon = 0;
        #1;
        assert(ALUoutput==-1343);
        $display("Passed Signed ADD Operation");
        #1;
        reg_read_a = 32'b11111111111111111111101010110111;
        alub = 10;
        unsign =0;
        ALUcon = 0;
        #1;
        assert(ALUoutput==4294965953);
        $display("Passed Unigned ADD Operation");
        #1;
        reg_read_a = 32'b11111111111111111111101010110111;
        alub = 10;
        unsign =0;
        ALUcon = 1;
        #1;
        assert(ALUoutput==-1363);
        assert(lt==1);
        $display("Passed Signed Sub Operation");
        #1;
        reg_read_a = 32'b11111111111111111111101010110111;
        alub = 10;
        unsign =1;
        ALUcon = 1;
        #1;
        assert(ALUoutput==4294965933);
        assert(lt==0);
        $display("Passed Unigned Sub Operation");
        reg_read_a = 32'b11111111111111111111101010110111;
        alub = 10;
        unsign =0;
        ALUcon = 4;
        #1;
        assert(ALUoutput==0);
        $display("Passed Signed SLT Operation");
        #1;
        reg_read_a = 10;
        alub = 32'b11111111111111111111101010110111;
        unsign =1;
        ALUcon = 4;
        #1;
        assert(ALUoutput==32'b1);
        $display("Passed Unigned SLT Operation");

        #1;
        unsign=0;
        ALUcon=5;
        reg_read_a = 32'b11111111111111111111101010110111;
        alub = 10;
        #1;
        assert(hi == 4294967293); //-3
        assert(lo == 4294967161); //-135
        $display("Passed Signed MULT Operation");
        #1;
        unsign=1;
        ALUcon=5;
        reg_read_a = 32'b11111111111111111111101010110111;
        alub = 10;
        #1;
        assert(hi==3);
        assert(lo==429496594);
        $display("Passed Unigned MULT Operation");
        #1;
        unsign =0;
        ALUcon=6;
        reg_read_a = 32'b11111111111111111111101010110111;
        alub=10;
        #1; 
        assert(hi==32'd4294967295); 
        assert(lo==32'd4294953766); 
        $display("Passed Signed MULT Operation");
        #1;
        unsign=1;
        #1;
        assert (hi==32'b1001);
        assert(lo==32'b11111111111111111100101100100110);
        $display("Passed Unsigned MULT Operation");
        #1
        reg_read_a = 32'b11111111111111111111101010110111;
        alub=10;
        ALUcon = 9;
        #1;
        assert(ALUoutput == 32'b00000000001111111111111111111110)
        #1;
        reg_read_a = 32'b11111111111111111111101010110111;
        alub=10;
        ALUcon = 10;
        #1;
        assert(ALUoutput == 32'b00000000001111111111111111111110);
        $display("Passed Extra SRA, SRL Operation");

        $finish(0);
    end
endmodule

alu_tb.vcd
$date
	Thu Dec  2 16:27:38 2021
$end
$version
	Icarus Verilog
$end
$timescale
	1s
$end
$scope module alu_tb $end
$var wire 1 ! lt $end
$var wire 32 " lo [31:0] $end
$var wire 32 # hi [31:0] $end
$var wire 1 $ eq $end
$var wire 32 % ALUoutput [31:0] $end
$var reg 4 & ALUcon [3:0] $end
$var reg 32 ' alub [31:0] $end
$var reg 32 ( reg_read_a [31:0] $end
$var reg 1 ) unsign $end
$scope module dut $end
$var wire 4 * ALUcon [3:0] $end
$var wire 32 + alub [31:0] $end
$var wire 32 , reg_read_a [31:0] $end
$var wire 1 ) unsign $end
$var reg 32 - ALUoutput [31:0] $end
$var reg 1 $ eq $end
$var reg 32 . hi [31:0] $end
$var reg 32 / lo [31:0] $end
$var reg 1 ! lt $end
$var reg 64 0 multiplier [63:0] $end
$upscope $end
$upscope $end
$enddefinitions $end
#0
$dumpvars
bx 0
bx /
bx .
bx -
bx ,
bx +
bx *
x)
bx (
bx '
bx &
bx %
x$
bx #
bx "
x!
$end
#1
b101100 %
b101100 -
b0 "
b0 /
b0 #
b0 .
0!
0$
b0 &
b0 *
b1010 '
b1010 +
b100010 (
b100010 ,
0)
#2
b11000 %
b11000 -
b1 &
b1 *
#3
b10 %
b10 -
b10 &
b10 *
#4
b101010 %
b101010 -
b11 &
b11 *
#5
b0 %
b0 -
b100 &
b100 *
#6
b11 "
b11 /
b100 #
b100 .
b101 &
b101 *
#7
b101010100 0
b101010100 "
b101010100 /
b0 #
b0 .
b110 &
b110 *
#8
b1000100000000000 %
b1000100000000000 -
b0 "
b0 /
b111 &
b111 *
#9
b101000 %
b101000 -
b1000 &
b1000 *
#10
b0 %
b0 -
b1001 &
b1001 *
#11
b1010 &
b1010 *
#13
b101100 %
b101100 -
b0 &
b0 *
b100010 '
b100010 +
b1010 (
b1010 ,
#14
1!
b11111111111111111111111111101000 %
b11111111111111111111111111101000 -
b1 &
b1 *
#15
b10 %
b10 -
0!
b10 &
b10 *
#16
b101010 %
b101010 -
b11 &
b11 *
#17
b1 %
b1 -
b100 &
b100 *
#18
b1010 #
b1010 .
b101 &
b101 *
#19
b101010100 "
b101010100 /
b0 #
b0 .
b110 &
b110 *
#20
b0 %
b0 -
b0 "
b0 /
b111 &
b111 *
#21
b101000 %
b101000 -
b1000 &
b1000 *
#22
b0 %
b0 -
b1001 &
b1001 *
#23
b1010 &
b1010 *
#24
b11111111111111111111101011000001 %
b11111111111111111111101011000001 -
b0 &
b0 *
b1010 '
b1010 +
b11111111111111111111101010110111 (
b11111111111111111111101010110111 ,
#28
1!
b11111111111111111111101010101101 %
b11111111111111111111101010101101 -
b1 &
b1 *
#30
0!
1)
#31
b0 %
b0 -
b100 &
b100 *
0)
#33
b1 %
b1 -
1)
b11111111111111111111101010110111 '
b11111111111111111111101010110111 +
b1010 (
b1010 ,
#35
b11111111111111111111111101111001 "
b11111111111111111111111101111001 /
b11111111111111111111111111111101 #
b11111111111111111111111111111101 .
b1010 '
b1010 +
b11111111111111111111101010110111 (
b11111111111111111111101010110111 ,
b101 &
b101 *
0)
#37
b11001100110011001100100010010 "
b11001100110011001100100010010 /
b11 #
b11 .
1)
#39
b1111111111111111111111111111111111111111111111111100101100100110 0
b11111111111111111100101100100110 "
b11111111111111111100101100100110 /
b11111111111111111111111111111111 #
b11111111111111111111111111111111 .
b110 &
b110 *
0)
#41
b100111111111111111111100101100100110 0
b11111111111111111100101100100110 "
b11111111111111111100101100100110 /
b1001 #
b1001 .
1)
#43
b1111111111111111111110 %
b1111111111111111111110 -
b0 "
b0 /
b0 #
b0 .
b1001 &
b1001 *
#45
b1010 &
b1010 *
